auto_blob_saver/CONST.py
auto_blob_saver/__init__.py
auto_blob_saver/__main__.py
auto_blob_saver/utils/__init__.py
auto_blob_saver/utils/run_tsschecker.py
auto_blob_saver-0.1.2.data/scripts/auto_blob_saver
auto_blob_saver-0.1.2.dist-info/LICENSE
auto_blob_saver-0.1.2.dist-info/METADATA
auto_blob_saver-0.1.2.dist-info/WHEEL
auto_blob_saver-0.1.2.dist-info/top_level.txt
auto_blob_saver-0.1.2.dist-info/RECORD
