Metadata-Version: 2.1
Name: auto-blob-saver
Version: 0.1.2
Summary: Save your blobs automatically.
Home-page: https://github.com/Helloyunho/auto-blob-saver
Author: Helloyunho
Author-email: yunho050840@gmail.com
License: UNKNOWN
Platform: UNKNOWN
Requires-Python: >=3.8
